zenodo_backpack/__init__.py
zenodo_backpack/version.py
zenodo_backpack-0.4.0.data/scripts/zenodo_backpack
zenodo_backpack-0.4.0.dist-info/licenses/LICENSE
zenodo_backpack-0.4.0.dist-info/METADATA
zenodo_backpack-0.4.0.dist-info/WHEEL
zenodo_backpack-0.4.0.dist-info/top_level.txt
zenodo_backpack-0.4.0.dist-info/RECORD
