Metadata-Version: 2.4
Name: zenodo_backpack
Version: 0.4.0
Summary: Manage data bundled with bioinformatic software through Zenodo DOI integration
Home-page: https://github.com/centre-for-microbiome-research/zenodo_backpack
Author: ['Alex Chklovski', 'Ben Woodcroft']
Author-email: chklovski@gmail.com
License: GPL3+
Classifier: Development Status :: 3 - Alpha
Classifier: Topic :: Scientific/Engineering
Classifier: Topic :: Scientific/Engineering :: Bio-Informatics
Classifier: License :: OSI Approved :: GNU General Public License v3 or later (GPLv3+)
Classifier: Programming Language :: Python :: 3
License-File: LICENSE
Requires-Dist: tqdm
Requires-Dist: requests
Dynamic: author
Dynamic: author-email
Dynamic: classifier
Dynamic: description
Dynamic: description-content-type
Dynamic: home-page
Dynamic: license
Dynamic: license-file
Dynamic: requires-dist
Dynamic: summary
